hqt/.version
hqt/__classpath__.py
hqt/__init__.py
hqt/qt_application.py
hqt/stream_capturer.py
hqt/promotions/__init__.py
hqt/promotions/hcombobox.py
hqt/promotions/hconsole.py
hqt/promotions/hframe.py
hqt/promotions/hlabel.py
hqt/promotions/hlistwidget.py
hqt/promotions/hstacked_widget.py
hqt/promotions/htablemodel.py
hqt/promotions/htableview.py
hqt/promotions/htoolbox.py
hqt/views/__init__.py
hqt/views/main_view.py
hqt/views/qt_view.py
hspylib_hqt-0.9.44.dist-info/METADATA
hspylib_hqt-0.9.44.dist-info/WHEEL
hspylib_hqt-0.9.44.dist-info/top_level.txt
hspylib_hqt-0.9.44.dist-info/RECORD
