Metadata-Version: 2.1
Name: hspylib-hqt
Version: 0.9.44
Summary: HsPyLib - QT framework extensions
Home-page: https://github.com/yorevs/hspylib
Author: Hugo Saporetti Junior
Author-email: yorevs@hotmail.com
License: MIT
Project-URL: GitHub, https://github.com/yorevs/hspylib
Project-URL: PyPi, https://pypi.org/project/hspylib-hqt/
Keywords: qt,ui,extensions,application,pyqt
Platform: Darwin
Platform: Linux
Classifier: License :: OSI Approved :: MIT License
Classifier: Programming Language :: Python :: 3.10
Classifier: Operating System :: MacOS :: MacOS X
Classifier: Operating System :: POSIX :: Linux
Classifier: Operating System :: Unix
Classifier: Development Status :: 3 - Alpha
Classifier: Environment :: Console
Classifier: Natural Language :: English
Classifier: Topic :: Terminals
Classifier: Topic :: Software Development :: Libraries :: Python Modules
Classifier: Topic :: Software Development :: Libraries :: Application Frameworks
Classifier: Intended Audience :: Developers
Requires-Python: >=3.10
Requires-Dist: hspylib
Requires-Dist: PyQt5 >=5.15.10
Requires-Dist: PyQt5-stubs >=5.15.6.0
Requires-Dist: pyperclip >=1.9.0
